LEDAutomation/Connections.py
LEDAutomation/Driver.py
LEDAutomation/Expanders.py
LEDAutomation/Hal.py
LEDAutomation/LedConsole.py
LEDAutomation/PLedConsole.py
LEDAutomation/USBs.py
LEDAutomation/__init__.py
LED_Automation-0.1.4.dist-info/METADATA
LED_Automation-0.1.4.dist-info/WHEEL
LED_Automation-0.1.4.dist-info/top_level.txt
LED_Automation-0.1.4.dist-info/RECORD
