Metadata-Version: 2.1
Name: LED-Automation
Version: 0.1.4
Summary: LED Automation library
Classifier: Programming Language :: Python
Classifier: Operating System :: OS Independent
Requires-Dist: numpy
